pyG5/__init__.py
pyG5/pyG5Main.py
pyG5/pyG5Network.py
pyG5/pyG5View.py
pyG5/pyG5ViewTester.py
pyG5-0.0.4.data/scripts/pyG5DualStacked
pyG5-0.0.4.dist-info/LICENSE.TXT
pyG5-0.0.4.dist-info/METADATA
pyG5-0.0.4.dist-info/WHEEL
pyG5-0.0.4.dist-info/top_level.txt
pyG5-0.0.4.dist-info/RECORD
