Metadata-Version: 2.1
Name: pyG5
Version: 0.0.4
Summary: PyQt5 application connecting to X-Plane flight simulator and displaying a garmin G5
Home-page: https://github.com/blauret/pyG5
Author: Ben Lauret
Author-email: ben@lauretland.com
License: MIT license
Keywords: X-Plane,python,PyQt5,Garmin,G5
Classifier: Development Status :: 2 - Pre-Alpha
Classifier: Intended Audience :: Developers
Classifier: License :: OSI Approved :: MIT License
Classifier: Natural Language :: English
Classifier: Programming Language :: Python :: 3.9
License-File: LICENSE.TXT
Requires-Dist: PySide6
